kirara_email/__init__.py
kirara_email/blocks.py
kirara_email/example/sendEmail.yaml
kirara_ai_email-0.3.1.dist-info/LICENSE
kirara_ai_email-0.3.1.dist-info/METADATA
kirara_ai_email-0.3.1.dist-info/WHEEL
kirara_ai_email-0.3.1.dist-info/entry_points.txt
kirara_ai_email-0.3.1.dist-info/top_level.txt
kirara_ai_email-0.3.1.dist-info/RECORD
