Metadata-Version: 2.1
Name: kirara-ai-email
Version: 0.3.1
Summary: 收发邮件 for lss233/chatgpt-mirai-qq-bot，提供收取未读邮件和发送邮件的block，首次发送或收取邮件请一并提供发件人邮箱和授权码（授权码获取路径：qq邮箱-设置-账号与安全-安全设置-开启服务-获取授权码）
Home-page: https://github.com/chuanSir123/kirara-ai-emial
Author: chuanSir
Author-email: 416448943@qq.com
Project-URL: Bug Tracker, https://github.com/chuanSir123/kirara-ai-emial/issues
Project-URL: Documentation, https://github.com/chuanSir123/kirara-ai-emial/wiki
Project-URL: Source Code, https://github.com/chuanSir123/kirara-ai-emial
Classifier: Programming Language :: Python :: 3
Classifier: License :: OSI Approved :: GNU Affero General Public License v3
Classifier: Operating System :: OS Independent
Requires-Python: >=3.8
License-File: LICENSE
Requires-Dist: msal
Requires-Dist: kirara-ai>=3.2.0
